{
  "appId": "myconsumption.atomy.com",
  "appName": "Atomy Consumer Survey",
  "webDir": "dist",
  "bundledWebRuntime": false,
  "windowsAndroidStudioPath": "C:\\Program Files\\Android\\Android Studio\\bin\\studio64.exe",
  "plugins": {
    "CapacitorUpdater": {
      "autoUpdateUrl": "https://capgo.app/api/latest?appid=myconsumption.atomy.com&channel=dev"
    },
    "SplashScreen": {
      "launchShowDuration": 3000,
      "launchAutoHide": true,
      "backgroundColor": "#ffffffff",
      "androidSplashResourceName": "splash",
      "androidScaleType": "CENTER_CROP",
      "showSpinner": true,
      "androidSpinnerStyle": "large",
      "iosSpinnerStyle": "small",
      "spinnerColor": "#999999",
      "splashFullScreen": true,
      "splashImmersive": true,
      "layoutName": "launch_screen",
      "useDialog": true
    }
  }
}


